ocp_cluster_login/__init__.py
ocp_cluster_login/main.py
ocp_cluster_login-0.1.0.dist-info/LICENSE
ocp_cluster_login-0.1.0.dist-info/METADATA
ocp_cluster_login-0.1.0.dist-info/WHEEL
ocp_cluster_login-0.1.0.dist-info/entry_points.txt
ocp_cluster_login-0.1.0.dist-info/top_level.txt
ocp_cluster_login-0.1.0.dist-info/RECORD
