Metadata-Version: 2.1
Name: ocp-cluster-login
Version: 0.1.0
Author: dimak98
Author-email: kazindevops@gmail.com
Project-URL: Source, https://github.com/dimak98/ocp-cluster-login
Project-URL: Tracker, https://github.com/dimak98/ocp-cluster-login/issues
Classifier: Programming Language :: Python :: 3
Classifier: License :: OSI Approved :: MIT License
Classifier: Operating System :: OS Independent
Requires-Python: >=3.6
License-File: LICENSE
Requires-Dist: selenium >=3.141.0
